odoo10_addon_web_tree_image-10.0.1.1.0-py2.7-nspkg.pth
odoo10_addon_web_tree_image-10.0.1.1.0.dist-info/top_level.txt
odoo10_addon_web_tree_image-10.0.1.1.0.dist-info/WHEEL
odoo10_addon_web_tree_image-10.0.1.1.0.dist-info/RECORD
odoo10_addon_web_tree_image-10.0.1.1.0.dist-info/metadata.json
odoo10_addon_web_tree_image-10.0.1.1.0.dist-info/DESCRIPTION.rst
odoo10_addon_web_tree_image-10.0.1.1.0.dist-info/METADATA
odoo10_addon_web_tree_image-10.0.1.1.0.dist-info/namespace_packages.txt
odoo/addons/web_tree_image/__manifest__.py
odoo/addons/web_tree_image/__init__.py
odoo/addons/web_tree_image/README.rst
odoo/addons/web_tree_image/view/assets.xml
odoo/addons/web_tree_image/static/description/icon.png
odoo/addons/web_tree_image/static/src/js/web_tree_image.js
odoo/addons/web_tree_image/static/src/xml/widget.xml
